clickzetta/__init__.py
clickzetta/client.py
clickzetta/enums.py
clickzetta/object_storage_client.py
clickzetta/proto_script.py
clickzetta/query_result.py
clickzetta/schema.py
clickzetta/session.py
clickzetta/standard_sql.py
clickzetta/table.py
clickzetta/utils.py
clickzetta/version.py
clickzetta/bulkload/__init__.py
clickzetta/bulkload/bulkload_api.py
clickzetta/bulkload/bulkload_enums.py
clickzetta/bulkload/bulkload_session.py
clickzetta/bulkload/bulkload_stream.py
clickzetta/bulkload/bulkload_writer.py
clickzetta/bulkload/cz_oss_filesystem.py
clickzetta/bulkload/cz_table.py
clickzetta/connector/__init__.py
clickzetta/connector/version.py
clickzetta/connector/common/notify_executor.py
clickzetta/connector/sqlalchemy/__init__.py
clickzetta/connector/sqlalchemy/_connector.py
clickzetta/connector/sqlalchemy/_helpers.py
clickzetta/connector/sqlalchemy/_types.py
clickzetta/connector/sqlalchemy/base.py
clickzetta/connector/sqlalchemy/datatype.py
clickzetta/connector/sqlalchemy/requirements.py
clickzetta/connector/superset/__init__.py
clickzetta/connector/superset/clickzetta.py
clickzetta/connector/v0/__init__.py
clickzetta/connector/v0/_bulkload.py
clickzetta/connector/v0/_dbapi.py
clickzetta/connector/v0/_dbapi_helpers.py
clickzetta/connector/v0/_helpers.py
clickzetta/connector/v0/_pandas_utils.py
clickzetta/connector/v0/_volume.py
clickzetta/connector/v0/client.py
clickzetta/connector/v0/connection.py
clickzetta/connector/v0/converter.py
clickzetta/connector/v0/cursor.py
clickzetta/connector/v0/dbapi.py
clickzetta/connector/v0/enums.py
clickzetta/connector/v0/exception.py
clickzetta/connector/v0/exceptions.py
clickzetta/connector/v0/object_storage_client.py
clickzetta/connector/v0/parse_url.py
clickzetta/connector/v0/query_result.py
clickzetta/connector/v0/schema.py
clickzetta/connector/v0/sql_types.py
clickzetta/connector/v0/standard_sql.py
clickzetta/connector/v0/table.py
clickzetta/connector/v0/types.py
clickzetta/connector/v0/utils.py
clickzetta/dbapi/__init__.py
clickzetta_connector-1.0.13.dist-info/LICENSE
clickzetta_connector-1.0.13.dist-info/METADATA
clickzetta_connector-1.0.13.dist-info/WHEEL
clickzetta_connector-1.0.13.dist-info/entry_points.txt
clickzetta_connector-1.0.13.dist-info/top_level.txt
clickzetta_connector-1.0.13.dist-info/RECORD
