Metadata-Version: 2.1
Name: clickzetta-connector
Version: 1.0.13
Summary: clickzetta python connector
Author-email: "wei.liu" <wei.liu@clickzetta.com>, "guantao.gao" <guantao.gao@clickzetta.com>, "lin.zhang" <lin.zhang@clickzetta.com>
License: Apache-2.0
Project-URL: documentation, https://www.yunqi.tech/
Platform: Posix
Platform: MacOS X
Classifier: Development Status :: 3 - Alpha
Requires-Python: >=3.7
License-File: LICENSE
Requires-Dist: proto-plus <2.0.0dev,>=1.22.0
Requires-Dist: packaging >=14.3
Requires-Dist: protobuf ==5.28.1
Requires-Dist: grpcio
Requires-Dist: apscheduler
Requires-Dist: python-dateutil <3.0dev,>=2.7.2
Requires-Dist: requests <3.0.0dev,>=2.21.0
Requires-Dist: pyarrow >=10.0.1
Requires-Dist: numpy >1.23.5
Requires-Dist: sqlalchemy >=1.4
Requires-Dist: pandas <=2.3.3,>=1.3.4
Requires-Dist: urllib3 <3.0,>=1.26.19
Requires-Dist: future
Requires-Dist: python-dateutil
Requires-Dist: importlib-metadata ; python_version < "3.8"
Provides-Extra: dev
Requires-Dist: pytest ; extra == 'dev'
Requires-Dist: sqlparse ; extra == 'dev'
Requires-Dist: grpcio ; extra == 'dev'
Requires-Dist: grpcio-tools ; extra == 'dev'
Requires-Dist: build ; extra == 'dev'
Requires-Dist: pytest-xdist ; extra == 'dev'
Requires-Dist: pytz ; extra == 'dev'
Requires-Dist: twine ; extra == 'dev'
Requires-Dist: setuptools ; extra == 'dev'
Requires-Dist: setuptools-scm ; extra == 'dev'
Requires-Dist: tomli ; extra == 'dev'
Requires-Dist: grpcio-tools <=1.66.0 ; extra == 'dev'
Requires-Dist: protoletariat ; extra == 'dev'
Requires-Dist: pyroaring ; extra == 'dev'
